OracleSqlORM/__init__.py
OracleSqlORM/__main__.py
OracleSqlORM/demo_classes.py
OracleSqlORM/py2sql.py
py_2_oracle_sql_orm-1.0.1.dist-info/METADATA
py_2_oracle_sql_orm-1.0.1.dist-info/WHEEL
py_2_oracle_sql_orm-1.0.1.dist-info/top_level.txt
py_2_oracle_sql_orm-1.0.1.dist-info/RECORD
