Metadata-Version: 2.1
Name: py-2-oracle-sql-orm
Version: 1.0.1
Summary: Python-Oracle SQL ORM
Home-page: UNKNOWN
Author: Alexandra Kmet, Stanislav Dzundza
License: UNKNOWN
Platform: UNKNOWN
Requires-Dist: cx-Oracle
